odoo/addons/sale_order_rename/README.rst
odoo/addons/sale_order_rename/__init__.py
odoo/addons/sale_order_rename/__manifest__.py
odoo/addons/sale_order_rename/i18n/sale_order_rename.pot
odoo/addons/sale_order_rename/models/__init__.py
odoo/addons/sale_order_rename/models/sale_order.py
odoo/addons/sale_order_rename/readme/CONTRIBUTORS.rst
odoo/addons/sale_order_rename/readme/DESCRIPTION.rst
odoo/addons/sale_order_rename/static/description/icon.png
odoo/addons/sale_order_rename/static/description/index.html
odoo/addons/sale_order_rename/tests/__init__.py
odoo/addons/sale_order_rename/tests/test_sale_order_rename.py
odoo/addons/sale_order_rename/views/sale_order.xml
odoo12_addon_sale_order_rename-12.0.1.0.2.dist-info/METADATA
odoo12_addon_sale_order_rename-12.0.1.0.2.dist-info/WHEEL
odoo12_addon_sale_order_rename-12.0.1.0.2.dist-info/top_level.txt
odoo12_addon_sale_order_rename-12.0.1.0.2.dist-info/RECORD
